mpl_template/__init__.py
mpl_template/template.py
mpl_template/tests/__init__.py
mpl_template/tests/test_template.py
mpl_template/tests/baseline_images/__init__.py
mpl_template/tests/baseline_images/grace_hopper.png
mpl_template/tests/baseline_images/test_blank.png
mpl_template/tests/baseline_images/test_custom_spans.png
mpl_template/tests/baseline_images/test_custom_titleblock.png
mpl_template/tests/baseline_images/test_fancy_titleblock.png
mpl_template/tests/baseline_images/test_insert_image_from_file.png
mpl_template/tests/baseline_images/test_insert_image_from_file_shrink_half.png
mpl_template/tests/baseline_images/test_insert_image_from_file_zoom_10x.png
mpl_template/tests/baseline_images/test_insert_image_from_file_zoom_10x_expand.png
mpl_template/tests/baseline_images/test_insert_image_from_url.png
mpl_template/tests/baseline_images/test_insert_image_from_url_shrink_half.png
mpl_template/tests/baseline_images/test_insert_image_from_url_zoom_10x.png
mpl_template/tests/baseline_images/test_insert_image_from_url_zoom_10x_expand.png
mpl_template/tests/baseline_images/test_titleblock_on_left.png
mpl_template/tests/baseline_images/test_zero_margins.png
mpl_template/tests/img/__init__.py
mpl_template/tests/img/grace_hopper_0.jpeg
mpl_template/tests/img/grace_hopper_1.jpeg
mpl_template/tests/img/grace_hopper_2.jpeg
mpl_template/tests/img/grace_hopper_3.jpeg
mpl_template/tests/img/polar_bar_demo.png
mpl_template-0.6.0.dist-info/LICENSE
mpl_template-0.6.0.dist-info/METADATA
mpl_template-0.6.0.dist-info/WHEEL
mpl_template-0.6.0.dist-info/top_level.txt
mpl_template-0.6.0.dist-info/RECORD
