Metadata-Version: 2.2
Name: mpl_template
Version: 0.6.0
Summary: mpl-template: matplotlib report template constructor
Author-email: Austin Orr <austinmartinorr@gmail.com>
License: BSD-3-Clause
Project-URL: Homepage, https://github.com/austinorr/mpl-template
Project-URL: Documentation, https://austinorr.github.io/mpl-template
Project-URL: Repository, https://github.com/austinorr/mpl-template
Project-URL: Issues, https://github.com/austinorr/mpl-template/issues
Classifier: License :: OSI Approved :: BSD License
Classifier: Operating System :: OS Independent
Classifier: Programming Language :: Python
Classifier: Intended Audience :: Science/Research
Classifier: Programming Language :: Python :: 3 :: Only
Classifier: Programming Language :: Python :: 3.10
Classifier: Programming Language :: Python :: 3.11
Classifier: Programming Language :: Python :: 3.12
Requires-Python: >=3.10
License-File: LICENSE
Requires-Dist: matplotlib>=2.5.0
Provides-Extra: all
Requires-Dist: requests; extra == "all"
Requires-Dist: pillow; extra == "all"
Provides-Extra: dev
Requires-Dist: mpl-template[all,docs]; extra == "dev"
Requires-Dist: matplotlib<3.11,>=3.10; extra == "dev"
Requires-Dist: coverage>=6.0.0; extra == "dev"
Requires-Dist: pytest>=7.0.0; extra == "dev"
Requires-Dist: pytest-cov>=4.1; extra == "dev"
Requires-Dist: pytest-mpl>=0.16.0; extra == "dev"
Requires-Dist: ruff>=0.1.4; extra == "dev"
Requires-Dist: pre-commit>=3.3; extra == "dev"
Provides-Extra: docs
Requires-Dist: sphinx; extra == "docs"
Requires-Dist: nbsphinx; extra == "docs"
Requires-Dist: sphinx-rtd-theme; extra == "docs"
Requires-Dist: seaborn; extra == "docs"
